[
    {
        "username": "gered32",
        "email": "niels.deliens3@gmail.com",
        "password_hash": "$2y$10$h2SHU17Pvson35QxwystUOzBnrK6JR8bLDvjlEDiV7kIXy4r2Bu5e",
        "created_at": "2026-01-26T13:39:52+01:00"
    },
    {
        "username": "kykylol24",
        "email": "ggeerreedd3322@gmail.com",
        "password_hash": "$2y$10$q4Dif1j98dgEWkAzkWdDAOJ88QJh5ASRSnl8Sw4uejU\/8eeuNPnMu",
        "created_at": "2026-01-26T13:44:08+01:00"
    },
    {
        "username": "aaa",
        "email": "aaa@aaa.com",
        "password_hash": "$2y$10$yrmz\/zOyI9EjQV3p6zUplO0pXZ81A0khSEmtf9LM7NnMkKhEqtN4m",
        "created_at": "2026-01-26T14:13:09+01:00"
    }
]